greenrefactor/__init__.py
greenrefactor/cli.py
greenrefactor/client.py
greenrefactor/core.py
greenrefactor/power_server.py
greenrefactor/providers/__init__.py
greenrefactor/providers/base.py
greenrefactor/providers/nvml_provider.py
greenrefactor/providers/powermetrics_provider.py
greenrefactor/providers/psutil_provider.py
greenrefactor/providers/rapl_provider.py
greenrefactor/providers/remote_provider.py
greenrefactor_python-0.3.11.dist-info/METADATA
greenrefactor_python-0.3.11.dist-info/WHEEL
greenrefactor_python-0.3.11.dist-info/entry_points.txt
greenrefactor_python-0.3.11.dist-info/RECORD
