Metadata-Version: 2.4
Name: greenrefactor-python
Version: 0.3.11
Summary: Cross-language lightweight SDK for Carbon Live / GreenRefactor dashboard
Project-URL: Homepage, https://github.com/aligokkaya/greenrefactor-python
Project-URL: Repository, https://github.com/aligokkaya/greenrefactor-python
Author: Ali Gökkaya
License: MIT
Classifier: License :: OSI Approved :: MIT License
Classifier: Operating System :: OS Independent
Classifier: Programming Language :: Python :: 3
Requires-Python: >=3.8
Requires-Dist: flask
Requires-Dist: psutil
Requires-Dist: websocket-client>=1.6.0
Requires-Dist: websockets
Provides-Extra: gpu
Requires-Dist: pynvml; extra == 'gpu'
